setup.cfg
setup.py
anircbot/__init__.py
anircbot/spam.py
anircbot/util.py
anircbot.egg-info/PKG-INFO
anircbot.egg-info/SOURCES.txt
anircbot.egg-info/dependency_links.txt
anircbot.egg-info/top_level.txt
anircbot/event/__init__.py
anircbot/event/commands.py
anircbot/event/replies.py
anircbot/logging/__init__.py
anircbot_flask/__init__.py