Metadata-Version: 1.0
Name: anircbot
Version: 0.1
Summary: An IRC Bot
Home-page: https://gitlab.com/cerebralpower/AnIRCBot
Author: Bill Schumacher
Author-email: bill@servernet.co
License: LGPLv3
Keywords: python irc bot
Platform: UNKNOWN
